{
  "name": "message_control",
  "version": "0.1.5",
  "last_date_update": "13.11.2022",
  "content": {
    "currency": "₽",
    "keyboard": {
      "back_main_search": "Закрыть",
      "main": {
        "search": "\uD83D\uDD0D Найти товар",
        "help": "❗ Помощь",
        "admin": "FALSE Управление",
        "favorite": "⭐ Избранное",
        "cart": "\uD83D\uDED2 Корзина",
        "login": "FALSE ⚠ Регицстрация ⚠",
        "profile": "FALSE \uD83D\uDD10 Мой аккаунт \uD83D\uDD10"
      },
      "search": {
        "brand": "По брендам",
        "category": "По категориям ",
        "list": "По всем товарам"
      },
      "profile": {
      },
      "product": {
      }
    },
    "command": {
      "start": "/start",
      "search": "/search",
      "help": "/help"
    },
    "message": {
      "search": {
        "main": "Как вы желаете искать?",
        "callback_brand": "выберите бренд",
        "callback_category": "выберите категорию"
      },
      "cart": {
        "null": "Ваша корзина пуста =("
      },
      "favorite": {
        "null": "Ваш список желаемого пуст =("
      },
      "help": "Опишите свою проблему",
      "complete": ", спасибо за регистрацию!\nХорошего дня и удачных покупок!",
      "new_user": "Добро пожаловать!\n\nПожалуйста пройдите регистрацию.",
      "welcome": ", добро пожаловать!"
    }
  }
}
